matmath/__init__.py
matmath/matrix.py
matmath/vector.py
matmath-3.2.0.dist-info/LICENSE
matmath-3.2.0.dist-info/METADATA
matmath-3.2.0.dist-info/WHEEL
matmath-3.2.0.dist-info/RECORD
